clickhouse_provider/__init__.py
clickhouse_provider/hooks/__init__.py
clickhouse_provider/hooks/client.py
clickhouse_provider/operators/__init__.py
clickhouse_provider/operators/query.py
clickhouse_provider/sensors/bool_sensor.py
airflow_provider_clickhouse_connect-0.0.13.dist-info/LICENSE
airflow_provider_clickhouse_connect-0.0.13.dist-info/METADATA
airflow_provider_clickhouse_connect-0.0.13.dist-info/WHEEL
airflow_provider_clickhouse_connect-0.0.13.dist-info/entry_points.txt
airflow_provider_clickhouse_connect-0.0.13.dist-info/top_level.txt
airflow_provider_clickhouse_connect-0.0.13.dist-info/RECORD
