Metadata-Version: 2.1
Name: airflow-provider-clickhouse-connect
Version: 0.0.13
Summary: Airflow Clickhouse Provider based on http connection
Author-email: Sergey Irin <serjdukareff@gmail.com>
License: Apache License 2.0
Project-URL: Source, https://github.com/RinSer/airflow-provider-clickhouse-connect/
Classifier: Development Status :: 4 - Beta
Classifier: Framework :: Apache Airflow
Classifier: Framework :: Apache Airflow :: Provider
Classifier: Intended Audience :: Developers
Classifier: License :: OSI Approved :: Apache Software License
Classifier: Programming Language :: Python :: 3.12
Requires-Python: ~=3.12
License-File: LICENSE
Requires-Dist: apache-airflow>=2.10
Requires-Dist: clickhouse-connect>=0.8.3
